tlg_app
