Metadata-Version: 2.1
Name: tlg-app-starco
Version: 1.5
Author: Mojtaba Tahmasbi
Requires-Dist: Starco==2.4
Requires-Dist: Telethon==1.32.1
Requires-Dist: phonenumbers
Requires-Dist: pycountry
Requires-Dist: nest-asyncio==1.5.8
